cuimage/__init__.py
cuimage/__main__.py
cuimage/cli.py
cuimage-0.0.0.dist-info/AUTHORS.rst
cuimage-0.0.0.dist-info/LICENSE
cuimage-0.0.0.dist-info/METADATA
cuimage-0.0.0.dist-info/WHEEL
cuimage-0.0.0.dist-info/entry_points.txt
cuimage-0.0.0.dist-info/top_level.txt
cuimage-0.0.0.dist-info/RECORD
