Metadata-Version: 2.1
Name: cuimage
Version: 0.0.0
Summary: A CUDA-accerlated image processing library
Home-page: https://github.com/gigony/cuimage
Author: Gigon Bae
Author-email: gigony@gmail.com
License: Apache-2.0
Project-URL: Documentation, https://cuimage.readthedocs.io/
Project-URL: Changelog, https://cuimage.readthedocs.io/en/latest/changelog.html
Project-URL: Issue Tracker, https://github.com/gigony/cuimage/issues
Platform: UNKNOWN
Classifier: Development Status :: 5 - Production/Stable
Classifier: Intended Audience :: Developers
Classifier: License :: OSI Approved :: Apache Software License
Classifier: Operating System :: Unix
Classifier: Operating System :: POSIX
Classifier: Operating System :: Microsoft :: Windows
Classifier: Programming Language :: Python
Classifier: Programming Language :: Python :: 2.7
Classifier: Programming Language :: Python :: 3
Classifier: Programming Language :: Python :: 3.5
Classifier: Programming Language :: Python :: 3.6
Classifier: Programming Language :: Python :: 3.7
Classifier: Programming Language :: Python :: 3.8
Classifier: Programming Language :: Python :: Implementation :: CPython
Classifier: Programming Language :: Python :: Implementation :: PyPy
Classifier: Topic :: Utilities
Requires-Python: >=2.7, !=3.0.*, !=3.1.*, !=3.2.*, !=3.3.*, !=3.4.*
Requires-Dist: click
